pagure_messages/__init__.py
pagure_messages/base.py
pagure_messages/git_schema.py
pagure_messages/issue_schema.py
pagure_messages/misc_schema.py
pagure_messages/project_schema.py
pagure_messages/pull_requests_schema.py
pagure_messages-1.3.0.dist-info/licenses/LICENSE
pagure_messages-1.3.0.dist-info/METADATA
pagure_messages-1.3.0.dist-info/WHEEL
pagure_messages-1.3.0.dist-info/entry_points.txt
pagure_messages-1.3.0.dist-info/top_level.txt
pagure_messages-1.3.0.dist-info/RECORD
