Metadata-Version: 2.4
Name: pagure-messages
Version: 1.3.0
Summary: A schema package for messages sent by pagure
Home-page: https://pagure.io/pagure
Maintainer: Fedora Infrastructure Team
Maintainer-email: infrastructure@lists.fedoraproject.org
License: GPLv2+
Keywords: fedora
Platform: Fedora
Platform: GNU/Linux
Classifier: License :: OSI Approved :: GNU General Public License v2 or later (GPLv2+)
Classifier: Operating System :: POSIX :: Linux
Classifier: Programming Language :: Python :: 3.9
Classifier: Programming Language :: Python :: 3.10
Classifier: Programming Language :: Python :: 3.11
Classifier: Programming Language :: Python :: 3.12
License-File: LICENSE
Requires-Dist: fedora_messaging
Dynamic: license-file
